{
    "pers00046": {
        "id": "pers00046",
        "primary": true,
        "occ": [
            "diplomat",
            "writer",
            "politician"
        ],
        "cerl": "https://data.cerl.org/thesaurus/cnp01296041",
        "wcat": "https://www.worldcat.org/identities/lccn-n83180262/",
        "viaf": "https://viaf.org/viaf/1141974/",
        "name": "Frere, John Hookham",
        "nat": "GB",
        "wd": "https://www.wikidata.org/wiki/Q6239771",
        "desc": "English diplomat and author (1769\u20131846)",
        "enwiki": "https://en.wikipedia.org/wiki/John_Hookham_Frere",
        "enwikisource": "https://en.wikisource.org/wiki/Author:John_Hookham_Frere",
        "texts": {
            "poems": [
                {
                    "text": "text00265",
                    "type": "orig",
                    "title": "The Rovers [Act I, scene 2]",
                    "work": "work00260",
                    "comp": "June 1798",
                    "publ": "1798"
                },
                {
                    "text": "text00271",
                    "type": "orig",
                    "title": "Whistlecraft [Canto III, st. 1 \u2013 7, 15 \u2013 19]",
                    "work": "work00265",
                    "comp": "1818",
                    "publ": "1818"
                }
            ],
            "prose": []
        }
    }
}