{
    "pers00130": {
        "id": "pers00130",
        "primary": true,
        "occ": [
            "essayist",
            "translator",
            "writer",
            "poet",
            "librettist"
        ],
        "cerl": "https://data.cerl.org/thesaurus/cnp02033960",
        "pseud": [
            "Pablo de Herlagn\u00e8z",
            "Pauvre Lelian"
        ],
        "europeana": "https://data.europeana.eu/agent/base/61297",
        "wcat": "https://www.worldcat.org/identities/lccn-n79043496/",
        "viaf": "https://viaf.org/viaf/4937684/",
        "name": "Verlaine, Paul",
        "nat": "FR",
        "wd": "https://www.wikidata.org/wiki/Q755",
        "desc": "French poet (1844\u20131896)",
        "enwiki": "https://en.wikipedia.org/wiki/Paul_Verlaine",
        "enwikisource": "https://en.wikisource.org/wiki/Author:Paul_Verlaine",
        "frwiki": "https://fr.wikipedia.org/wiki/Paul_Verlaine",
        "frwikisource": "https://fr.wikisource.org/wiki/Auteur:Paul_Verlaine",
        "otw": [
            {
                "title": "El\u00e9gies / Paul Verlaine.",
                "url": "http://purl.ox.ac.uk/uuid/e5795a4fcddd4b56865adccc3777ba6a",
                "date": "1893"
            },
            {
                "title": "Po\u00e8mes saturniens",
                "url": "https://archive.org/details/bub_gb_nkM-AQAAMAAJ",
                "date": "1894",
                "iiif": "https://iiif.archivelab.org/iiif/bub_gb_nkM-AQAAMAAJ/manifest.json"
            }
        ],
        "texts": {
            "poems": [
                {
                    "text": "text01459",
                    "type": "trans_eng",
                    "title": "Il Pleut Doucement sur la Ville",
                    "work": "work01025",
                    "comp": "",
                    "publ": ""
                },
                {
                    "text": "text01461",
                    "type": "trans_eng",
                    "title": "Spleen",
                    "work": "work01026",
                    "comp": "",
                    "publ": ""
                },
                {
                    "text": "text01463",
                    "type": "trans_eng",
                    "title": "The Sky is up Above the Roof",
                    "work": "work01027",
                    "comp": "",
                    "publ": ""
                },
                {
                    "text": "text01465",
                    "type": "trans_eng",
                    "title": "A Clymene",
                    "work": "work01028",
                    "comp": "",
                    "publ": ""
                },
                {
                    "text": "text01467",
                    "type": "trans_eng",
                    "title": "Fantoches",
                    "work": "work01029",
                    "comp": "",
                    "publ": ""
                },
                {
                    "text": "text01469",
                    "type": "trans_eng",
                    "title": "Pantomime",
                    "work": "work01030",
                    "comp": "",
                    "publ": ""
                },
                {
                    "text": "text01471",
                    "type": "trans_eng",
                    "title": "Cythere",
                    "work": "work01031",
                    "comp": "",
                    "publ": ""
                },
                {
                    "text": "text01473",
                    "type": "trans_eng",
                    "title": "Dans L\u2019Allee",
                    "work": "work01032",
                    "comp": "",
                    "publ": ""
                },
                {
                    "text": "text01475",
                    "type": "trans_eng",
                    "title": "Mandoline",
                    "work": "work01033",
                    "comp": "",
                    "publ": ""
                },
                {
                    "text": "text01477",
                    "type": "trans_eng",
                    "title": "Clair de Lune",
                    "work": "work01034",
                    "comp": "",
                    "publ": ""
                },
                {
                    "text": "text01479",
                    "type": "trans_eng",
                    "title": "A La Promenade",
                    "work": "work01035",
                    "comp": "",
                    "publ": ""
                },
                {
                    "text": "text01481",
                    "type": "trans_eng",
                    "title": "Cortege",
                    "work": "work01036",
                    "comp": "",
                    "publ": ""
                }
            ],
            "prose": []
        }
    }
}