{
    "pers00675": {
        "id": "pers00675",
        "primary": true,
        "occ": [
            "writer",
            "poet",
            "journalist"
        ],
        "cerl": "https://data.cerl.org/thesaurus/cnp01275968",
        "viaf": "https://viaf.org/viaf/147994428/",
        "name": "Granados, Mar\u00eda Josefa Garcia",
        "nat": "GT",
        "wd": "https://www.wikidata.org/wiki/Q6782028",
        "desc": "Guatemalan writer",
        "enwiki": "https://en.wikipedia.org/wiki/Mar%C3%ADa_Josefa_Garc%C3%ADa_Granados",
        "eswiki": "https://es.wikipedia.org/wiki/Mar%C3%ADa_Josefa_Garc%C3%ADa_Granados"
    }
}