{
    "erpa-0967070": [
        "erpa-0969630"
    ],
    "erpa-0967130": [
        "erpa-0969700"
    ],
    "erpa-0967140": [
        "erpa-0969720"
    ],
    "erpa-0967220": [
        "erpa-0969790"
    ],
    "erpa-0967150": [
        "erpa-0969730"
    ],
    "erpa-0967120": [
        "erpa-0969680",
        "erpa-0969690"
    ],
    "erpa-0967270": [
        "erpa-0969840"
    ],
    "erpa-0967230": [
        "erpa-0969800"
    ],
    "erpa-0967170": [
        "erpa-0969760"
    ],
    "erpa-0967160": [
        "erpa-0969740"
    ],
    "erpa-0967280": [
        "erpa-0969850"
    ],
    "erpa-0967240": [
        "erpa-0969810"
    ],
    "erpa-0967200": [
        "erpa-0969770",
        "erpa-0969790"
    ],
    "erpa-0967290": [
        "erpa-0969860"
    ],
    "erpa-0967250": [
        "erpa-0969820"
    ],
    "erpa-0967100": [
        "erpa-0969660"
    ],
    "erpa-0967110": [
        "erpa-0969670"
    ],
    "erpa-0967210": [
        "erpa-0969780"
    ],
    "erpa-0967260": [
        "erpa-0969830"
    ],
    "erpa-0967380": [
        "erpa-0969930"
    ],
    "erpa-0967420": [
        "erpa-0969960"
    ],
    "erpa-0967460": [
        "erpa-0970000"
    ],
    "erpa-0967350": [
        "erpa-0969920"
    ],
    "erpa-0967310": [
        "erpa-0969890"
    ],
    "erpa-0967430": [
        "erpa-0969970"
    ],
    "erpa-0967400": [
        "erpa-0969950"
    ],
    "erpa-0967470": [
        "erpa-0970020"
    ],
    "erpa-0967450": [
        "erpa-0969990"
    ],
    "erpa-0967440": [
        "erpa-0969980"
    ],
    "erpa-0967330": [
        "erpa-0969910"
    ],
    "erpa-0967390": [
        "erpa-0969940"
    ],
    "erpa-0967490": [
        "erpa-0970030"
    ],
    "erpa-0967550": [
        "erpa-0970100"
    ],
    "erpa-0967640": [
        "erpa-0970140"
    ],
    "erpa-0967580": [
        "erpa-0970130"
    ],
    "erpa-0967570": [
        "erpa-0970110"
    ],
    "erpa-0967510": [
        "erpa-0970060"
    ],
    "erpa-0967610": [
        "erpa-0970100"
    ],
    "erpa-0967520": [
        "erpa-0970070"
    ],
    "erpa-0967600": [
        "erpa-0970120"
    ],
    "erpa-0967680": [
        "erpa-0970190"
    ],
    "erpa-0967530": [
        "erpa-0970090"
    ],
    "erpa-0967660": [
        "erpa-0970160"
    ],
    "erpa-0967650": [
        "erpa-0970150"
    ],
    "erpa-0967540": [
        "erpa-0970080"
    ],
    "erpa-0967700": [
        "erpa-0970210"
    ],
    "erpa-0967670": [
        "erpa-0970170"
    ],
    "erpa-0967810": [
        "erpa-0970340"
    ],
    "erpa-0967800": [
        "erpa-0970320"
    ],
    "erpa-0967820": [
        "erpa-0970350"
    ],
    "erpa-0967750": [
        "erpa-0970280"
    ],
    "erpa-0967790": [
        "erpa-0970310"
    ],
    "erpa-0967720": [
        "erpa-0970240"
    ],
    "erpa-0967730": [
        "erpa-0970250"
    ],
    "erpa-0967830": [
        "erpa-0970330",
        "erpa-0970300"
    ],
    "erpa-0967770": [
        "erpa-0970310"
    ],
    "erpa-0967760": [
        "erpa-0970290"
    ],
    "erpa-0967840": [
        "erpa-0970360"
    ],
    "erpa-0967740": [
        "erpa-0970260"
    ],
    "erpa-0967780": [
        "erpa-0970270"
    ],
    "erpa-0967940": [
        "erpa-0970430"
    ],
    "erpa-0967930": [
        "erpa-0970440"
    ],
    "erpa-0967860": [
        "erpa-0970390"
    ],
    "erpa-0967900": [
        "erpa-0970420"
    ],
    "erpa-0967920": [
        "erpa-0970500"
    ],
    "erpa-0967870": [
        "erpa-0970400"
    ],
    "erpa-0967950": [
        "erpa-0970450"
    ],
    "erpa-0967990": [
        "erpa-0970490"
    ],
    "erpa-0967960": [
        "erpa-0970460"
    ],
    "erpa-0967980": [
        "erpa-0970480"
    ],
    "erpa-0968020": [
        "erpa-0970530"
    ],
    "erpa-0967890": [
        "erpa-0970520",
        "erpa-0970410"
    ],
    "erpa-0968000": [
        "erpa-0970510"
    ],
    "erpa-0967880": [
        "erpa-0970500"
    ],
    "erpa-0967970": [
        "erpa-0970470"
    ],
    "erpa-0968080": [
        "erpa-0970600"
    ],
    "erpa-0968090": [
        "erpa-0970610"
    ],
    "erpa-0968140": [
        "erpa-0970640"
    ],
    "erpa-0968040": [
        "erpa-0970560"
    ],
    "erpa-0968160": [
        "erpa-0970660",
        "erpa-0970670",
        "erpa-0970640"
    ],
    "erpa-0968050": [
        "erpa-0970570"
    ],
    "erpa-0968070": [
        "erpa-0970590"
    ],
    "erpa-0968170": [
        "erpa-0970680"
    ],
    "erpa-0968060": [
        "erpa-0970580"
    ],
    "erpa-0968130": [
        "erpa-0970630"
    ],
    "erpa-0968220": [
        "erpa-0970750"
    ],
    "erpa-0968270": [
        "erpa-0970810"
    ],
    "erpa-0968290": [
        "erpa-0970840",
        "erpa-0970830"
    ],
    "erpa-0968260": [
        "erpa-0970800"
    ],
    "erpa-0968250": [
        "erpa-0970780"
    ],
    "erpa-0968230": [
        "erpa-0970760"
    ],
    "erpa-0968240": [
        "erpa-0970770"
    ],
    "erpa-0968210": [
        "erpa-0970730"
    ],
    "erpa-0968280": [
        "erpa-0970820"
    ],
    "erpa-0968300": [
        "erpa-0970850"
    ],
    "erpa-0968200": [
        "erpa-0970740"
    ],
    "erpa-0968420": [
        "erpa-0970990",
        "erpa-0971020"
    ],
    "erpa-0968460": [
        "erpa-0971020",
        "erpa-0971010",
        "erpa-0971030"
    ],
    "erpa-0968350": [
        "erpa-0970920"
    ],
    "erpa-0968320": [
        "erpa-0970880"
    ],
    "erpa-0968440": [
        "erpa-0971030"
    ],
    "erpa-0968330": [
        "erpa-0970890"
    ],
    "erpa-0968430": [
        "erpa-0971000"
    ],
    "erpa-0968380": [
        "erpa-0970950"
    ],
    "erpa-0968470": [
        "erpa-0971040"
    ],
    "erpa-0968370": [
        "erpa-0970940"
    ],
    "erpa-0968340": [
        "erpa-0970900"
    ],
    "erpa-0968400": [
        "erpa-0970930"
    ],
    "erpa-0968390": [
        "erpa-0970960"
    ],
    "erpa-0968640": [
        "erpa-0971180"
    ],
    "erpa-0968590": [
        "erpa-0971150"
    ],
    "erpa-0968530": [
        "erpa-0971100"
    ],
    "erpa-0968520": [
        "erpa-0971080"
    ],
    "erpa-0968490": [
        "erpa-0971070"
    ],
    "erpa-0968540": [
        "erpa-0971110"
    ],
    "erpa-0968600": [
        "erpa-0971160"
    ],
    "erpa-0968630": [
        "erpa-0971170"
    ],
    "erpa-0968650": [
        "erpa-0971190"
    ],
    "erpa-0968570": [
        "erpa-0971130"
    ],
    "erpa-0968510": [
        "erpa-0971090"
    ],
    "erpa-0968560": [
        "erpa-0971120"
    ],
    "erpa-0968580": [
        "erpa-0971140"
    ],
    "erpa-0968620": [
        "erpa-0971180"
    ],
    "erpa-0968710": [
        "erpa-0971260"
    ],
    "erpa-0968750": [
        "erpa-0971300"
    ],
    "erpa-0968720": [
        "erpa-0971270"
    ],
    "erpa-0968810": [
        "erpa-0971360"
    ],
    "erpa-0968740": [
        "erpa-0971290"
    ],
    "erpa-0968830": [
        "erpa-0971380"
    ],
    "erpa-0968670": [
        "erpa-0971220"
    ],
    "erpa-0968760": [
        "erpa-0971310"
    ],
    "erpa-0968680": [
        "erpa-0971230"
    ],
    "erpa-0968800": [
        "erpa-0971350"
    ],
    "erpa-0968690": [
        "erpa-0971250"
    ],
    "erpa-0968770": [
        "erpa-0971320"
    ],
    "erpa-0968700": [
        "erpa-0971250",
        "erpa-0971240"
    ],
    "erpa-0968790": [
        "erpa-0971340"
    ],
    "erpa-0968730": [
        "erpa-0971280"
    ],
    "erpa-0968780": [
        "erpa-0971330"
    ],
    "erpa-0968820": [
        "erpa-0971370"
    ],
    "erpa-0968890": [
        "erpa-0971450",
        "erpa-0971430"
    ],
    "erpa-0968950": [
        "erpa-0971500"
    ],
    "erpa-0968910": [
        "erpa-0971460"
    ],
    "erpa-0968850": [
        "erpa-0971410"
    ],
    "erpa-0968930": [
        "erpa-0971480"
    ],
    "erpa-0968960": [
        "erpa-0971510"
    ],
    "erpa-0968860": [
        "erpa-0971420"
    ],
    "erpa-0969000": [
        "erpa-0971540"
    ],
    "erpa-0969010": [
        "erpa-0971550"
    ],
    "erpa-0968940": [
        "erpa-0971490"
    ],
    "erpa-0968980": [
        "erpa-0971470"
    ],
    "erpa-0968900": [
        "erpa-0971440"
    ],
    "erpa-0968970": [
        "erpa-0971520"
    ],
    "erpa-0968990": [
        "erpa-0971530"
    ],
    "erpa-0969070": [
        "erpa-0971620"
    ],
    "erpa-0969150": [
        "erpa-0971690"
    ],
    "erpa-0969140": [
        "erpa-0971680"
    ],
    "erpa-0969090": [
        "erpa-0971630"
    ],
    "erpa-0969030": [
        "erpa-0971580"
    ],
    "erpa-0969040": [
        "erpa-0971590"
    ],
    "erpa-0969080": [
        "erpa-0971650"
    ],
    "erpa-0969050": [
        "erpa-0971610"
    ],
    "erpa-0969100": [
        "erpa-0971640"
    ],
    "erpa-0969120": [
        "erpa-0971660"
    ],
    "erpa-0969160": [
        "erpa-0971700"
    ],
    "erpa-0969130": [
        "erpa-0971670"
    ],
    "erpa-0969060": [
        "erpa-0971600"
    ],
    "erpa-0969220": [
        "erpa-0971770"
    ],
    "erpa-0969230": [
        "erpa-0971780"
    ],
    "erpa-0969290": [
        "erpa-0971830"
    ],
    "erpa-0969320": [
        "erpa-0971850"
    ],
    "erpa-0969180": [
        "erpa-0971730"
    ],
    "erpa-0969260": [
        "erpa-0971800"
    ],
    "erpa-0969270": [
        "erpa-0971820"
    ],
    "erpa-0969190": [
        "erpa-0971740"
    ],
    "erpa-0969330": [
        "erpa-0971860"
    ],
    "erpa-0969280": [
        "erpa-0971830"
    ],
    "erpa-0969210": [
        "erpa-0971760"
    ],
    "erpa-0969200": [
        "erpa-0971750"
    ],
    "erpa-0969240": [
        "erpa-0971790"
    ],
    "erpa-0969300": [
        "erpa-0971840"
    ],
    "erpa-0969250": [
        "erpa-0971810"
    ],
    "erpa-0969390": [
        "erpa-0971930"
    ],
    "erpa-0969440": [
        "erpa-0971990"
    ],
    "erpa-0969400": [
        "erpa-0971940"
    ],
    "erpa-0969420": [
        "erpa-0971960"
    ],
    "erpa-0969500": [
        "erpa-0972030"
    ],
    "erpa-0969350": [
        "erpa-0971890"
    ],
    "erpa-0969510": [
        "erpa-0972050"
    ],
    "erpa-0969360": [
        "erpa-0971900"
    ],
    "erpa-0969480": [
        "erpa-0972020"
    ],
    "erpa-0969380": [
        "erpa-0971920"
    ],
    "erpa-0969430": [
        "erpa-0971980"
    ],
    "erpa-0969470": [
        "erpa-0972010"
    ],
    "erpa-0969370": [
        "erpa-0971910"
    ],
    "erpa-0969410": [
        "erpa-0971950"
    ],
    "erpa-0969490": [
        "erpa-0972040"
    ]
}