{
    "erpa-0784200": [
        "erpa-0786020"
    ],
    "erpa-0784190": [
        "erpa-0786000"
    ],
    "erpa-0784240": [
        "erpa-0786070"
    ],
    "erpa-0784210": [
        "erpa-0786030"
    ],
    "erpa-0784230": [
        "erpa-0786010"
    ],
    "erpa-0784590": [
        "erpa-0786470"
    ],
    "erpa-0785430": [
        "erpa-0787170"
    ],
    "erpa-0785260": [
        "erpa-0787100",
        "erpa-0787190"
    ],
    "erpa-0784520": [
        "erpa-0786510"
    ],
    "erpa-0785790": [
        "erpa-0787550"
    ],
    "erpa-0785490": [
        "erpa-0787230"
    ],
    "erpa-0785100": [
        "erpa-0786860"
    ],
    "erpa-0785270": [
        "erpa-0787020"
    ],
    "erpa-0785200": [
        "erpa-0786960",
        "erpa-0787240"
    ],
    "erpa-0785750": [
        "erpa-0787510"
    ],
    "erpa-0784900": [
        "erpa-0786710"
    ],
    "erpa-0785230": [
        "erpa-0786980"
    ],
    "erpa-0784910": [
        "erpa-0786720"
    ],
    "erpa-0784960": [
        "erpa-0786680"
    ],
    "erpa-0785800": [
        "erpa-0787560"
    ],
    "erpa-0784560": [
        "erpa-0786440"
    ],
    "erpa-0784720": [
        "erpa-0786400"
    ],
    "erpa-0784920": [
        "erpa-0786730"
    ],
    "erpa-0785560": [
        "erpa-0787310"
    ],
    "erpa-0785500": [
        "erpa-0787240"
    ],
    "erpa-0785760": [
        "erpa-0787520"
    ],
    "erpa-0785380": [
        "erpa-0787130",
        "erpa-0787120"
    ],
    "erpa-0784450": [
        "erpa-0786220"
    ],
    "erpa-0785340": [
        "erpa-0787090",
        "erpa-0787180"
    ],
    "erpa-0784970": [
        "erpa-0786690"
    ],
    "erpa-0785610": [
        "erpa-0787360"
    ],
    "erpa-0784360": [
        "erpa-0786130"
    ],
    "erpa-0784270": [
        "erpa-0786100"
    ],
    "erpa-0785010": [
        "erpa-0786780"
    ],
    "erpa-0784380": [
        "erpa-0786190",
        "erpa-0786180"
    ],
    "erpa-0784930": [
        "erpa-0786740"
    ],
    "erpa-0785150": [
        "erpa-0786890"
    ],
    "erpa-0784890": [
        "erpa-0786700"
    ],
    "erpa-0785280": [
        "erpa-0787040"
    ],
    "erpa-0785350": [
        "erpa-0787190"
    ],
    "erpa-0784470": [
        "erpa-0786270"
    ],
    "erpa-0784750": [
        "erpa-0786430"
    ],
    "erpa-0785520": [
        "erpa-0787350"
    ],
    "erpa-0785710": [
        "erpa-0787480"
    ],
    "erpa-0784670": [
        "erpa-0786480",
        "erpa-0786350"
    ],
    "erpa-0784320": [
        "erpa-0786260"
    ],
    "erpa-0784840": [
        "erpa-0786640"
    ],
    "erpa-0785030": [
        "erpa-0786770"
    ],
    "erpa-0785670": [
        "erpa-0787440"
    ],
    "erpa-0784500": [
        "erpa-0786590"
    ],
    "erpa-0784540": [
        "erpa-0786500"
    ],
    "erpa-0784690": [
        "erpa-0786570"
    ],
    "erpa-0784480": [
        "erpa-0786280"
    ],
    "erpa-0784700": [
        "erpa-0786580"
    ],
    "erpa-0785590": [
        "erpa-0787330"
    ],
    "erpa-0784770": [
        "erpa-0786450"
    ],
    "erpa-0785060": [
        "erpa-0786810"
    ],
    "erpa-0784990": [
        "erpa-0786750"
    ],
    "erpa-0784550": [
        "erpa-0786510"
    ],
    "erpa-0785810": [
        "erpa-0787570"
    ],
    "erpa-0785600": [
        "erpa-0787340"
    ],
    "erpa-0784730": [
        "erpa-0786410"
    ],
    "erpa-0785690": [
        "erpa-0787460"
    ],
    "erpa-0785390": [
        "erpa-0787050",
        "erpa-0787270",
        "erpa-0787130"
    ],
    "erpa-0784850": [
        "erpa-0786790"
    ],
    "erpa-0785700": [
        "erpa-0787470"
    ],
    "erpa-0785650": [
        "erpa-0787420"
    ],
    "erpa-0785820": [
        "erpa-0787580"
    ],
    "erpa-0784820": [
        "erpa-0786610"
    ],
    "erpa-0785630": [
        "erpa-0787350"
    ],
    "erpa-0785540": [
        "erpa-0787290"
    ],
    "erpa-0784390": [
        "erpa-0786200"
    ],
    "erpa-0784330": [
        "erpa-0786340"
    ],
    "erpa-0784680": [
        "erpa-0786560",
        "erpa-0786480"
    ],
    "erpa-0784760": [
        "erpa-0786390"
    ],
    "erpa-0785020": [
        "erpa-0786760"
    ],
    "erpa-0784630": [
        "erpa-0786320"
    ],
    "erpa-0784830": [
        "erpa-0786620"
    ],
    "erpa-0785680": [
        "erpa-0787450"
    ],
    "erpa-0785300": [
        "erpa-0787060"
    ],
    "erpa-0785070": [
        "erpa-0786830",
        "erpa-0786820"
    ],
    "erpa-0785240": [
        "erpa-0786990"
    ],
    "erpa-0785410": [
        "erpa-0787150"
    ],
    "erpa-0784280": [
        "erpa-0786120"
    ],
    "erpa-0784800": [
        "erpa-0786590"
    ],
    "erpa-0784570": [
        "erpa-0786360",
        "erpa-0786350"
    ],
    "erpa-0785080": [
        "erpa-0786840"
    ],
    "erpa-0784310": [
        "erpa-0786110"
    ],
    "erpa-0785530": [
        "erpa-0787280"
    ],
    "erpa-0785420": [
        "erpa-0787160"
    ],
    "erpa-0784610": [
        "erpa-0786390"
    ],
    "erpa-0784370": [
        "erpa-0786170"
    ],
    "erpa-0785090": [
        "erpa-0786850"
    ],
    "erpa-0785640": [
        "erpa-0787400"
    ],
    "erpa-0785740": [
        "erpa-0787500"
    ],
    "erpa-0785220": [
        "erpa-0786970"
    ],
    "erpa-0785310": [
        "erpa-0787090",
        "erpa-0787270"
    ],
    "erpa-0784530": [
        "erpa-0786520"
    ],
    "erpa-0784290": [
        "erpa-0786240"
    ],
    "erpa-0785550": [
        "erpa-0787300"
    ],
    "erpa-0785130": [
        "erpa-0786870"
    ],
    "erpa-0785400": [
        "erpa-0787140"
    ],
    "erpa-0784350": [
        "erpa-0786150"
    ],
    "erpa-0785180": [
        "erpa-0786950"
    ],
    "erpa-0785250": [
        "erpa-0787000"
    ],
    "erpa-0784580": [
        "erpa-0786370",
        "erpa-0786460"
    ],
    "erpa-0784740": [
        "erpa-0786420"
    ],
    "erpa-0785720": [
        "erpa-0787320"
    ],
    "erpa-0785780": [
        "erpa-0787540"
    ],
    "erpa-0785730": [
        "erpa-0787490"
    ],
    "erpa-0785660": [
        "erpa-0787430"
    ]
}