{
    "pers00018": {
        "id": "pers00018",
        "occ": [
            "poet",
            "writer"
        ],
        "cerl": "https://data.cerl.org/thesaurus/cnp01442343",
        "europeana": "https://data.europeana.eu/agent/base/61475",
        "wcat": "https://www.worldcat.org/identities/lccn-n79078189/",
        "bibl": [
            {
                "title": "The poetical works of Mrs. Hemans.",
                "url": "https://archive.org/details/poeticalworksofm00hema_0",
                "date": "1800",
                "iiif": "https://iiif.archivelab.org/iiif/poeticalworksofm00hema_0/manifest.json"
            },
            {
                "title": "Poems, by Felicia Dorothea Browne.",
                "url": "https://hdl.handle.net/2027/nyp.33433000181002",
                "date": "1808"
            },
            {
                "title": "The domestic affections and other poems / by Felicia Dorothea Browne.",
                "url": "https://hdl.handle.net/2027/uc1.$b173241",
                "date": "1812"
            },
            {
                "title": "The restoration of the works of art to Italy: a poem, by a lady [F.D. Hemans].",
                "url": "http://purl.ox.ac.uk/uuid/d1355302eb5840cb8fb8635383a5cbb5",
                "date": "1816"
            },
            {
                "title": "The restoration of the works of art to Italy; a poem.",
                "url": "https://hdl.handle.net/2027/uc2.ark:/13960/t6736rd5t",
                "date": "1816"
            },
            {
                "title": "The restoration of the works of art to Italy; a poem",
                "url": "https://archive.org/details/restorationofwor00hema",
                "date": "1816",
                "iiif": "https://iiif.archivelab.org/iiif/restorationofwor00hema/manifest.json"
            },
            {
                "title": "The restoration of the works of art to Italy : a poem",
                "url": "https://archive.org/details/restorationofwor00hemarich",
                "date": "1816",
                "iiif": "https://iiif.archivelab.org/iiif/restorationofwor00hemarich/manifest.json"
            },
            {
                "title": "Modern Greece, a poem [by F.D. Hemans].",
                "url": "http://purl.ox.ac.uk/uuid/5fc725cacf084659a03fc76649db96a7",
                "date": "1817"
            },
            {
                "title": "Translations from Camoens",
                "url": "https://archive.org/details/translationsfrom00hemarich",
                "date": "1818",
                "iiif": "https://iiif.archivelab.org/iiif/translationsfrom00hemarich/manifest.json"
            },
            {
                "title": "Tales, and historic scenes, in verse.",
                "url": "http://purl.ox.ac.uk/uuid/fc2f8d0d81de4275a2adf2cc457342b4",
                "date": "1819"
            },
            {
                "title": "Tales and historic scenes in verse",
                "url": "https://archive.org/details/taleshistoricsce00hemaiala",
                "date": "1819",
                "iiif": "https://iiif.archivelab.org/iiif/taleshistoricsce00hemaiala/manifest.json"
            },
            {
                "title": "Tales and historic scenes in verse / by Felicia Hermans.",
                "url": "https://hdl.handle.net/2027/uc1.$b173260",
                "date": "1819"
            },
            {
                "title": "Tales and historic scenes in verse / by Felicia Hermans.",
                "url": "https://hdl.handle.net/2027/uc2.ark:/13960/t57d2tm7m",
                "date": "1819"
            },
            {
                "title": "Stanzas to the memory of the late king.",
                "url": "http://purl.ox.ac.uk/uuid/92174af1685e49289db6e8e2a4262d2f",
                "date": "1820"
            },
            {
                "title": "The siege of Valencia; a dramatic poem. The last Constantine: with other poems.",
                "url": "http://purl.ox.ac.uk/uuid/ee6a0fa6dfa540e8a9a8f12c0cfe9b7b",
                "date": "1823"
            },
            {
                "title": "The vespers of Palermo : a tragedy in five acts",
                "url": "https://archive.org/details/vespersofpalermo00hemarich",
                "date": "1823",
                "iiif": "https://iiif.archivelab.org/iiif/vespersofpalermo00hemarich/manifest.json"
            },
            {
                "title": "The vespers of Palermo : a tragedy in five acts",
                "url": "https://archive.org/details/vesperspalermoa00hemagoog",
                "date": "1823",
                "iiif": "https://iiif.archivelab.org/iiif/vesperspalermoa00hemagoog/manifest.json"
            },
            {
                "title": "The forest sanctuary; and other poems.",
                "url": "http://purl.ox.ac.uk/uuid/5039bb190b8d4e19bdecde2ba2bda0da",
                "date": "1825"
            },
            {
                "title": "The forest sanctuary : and other poems.",
                "url": "https://archive.org/details/forestsanctuaryo00hemarich",
                "date": "1825",
                "iiif": "https://iiif.archivelab.org/iiif/forestsanctuaryo00hemarich/manifest.json"
            },
            {
                "title": "Poems",
                "url": "https://archive.org/details/poems04hemagoog",
                "date": "1827",
                "iiif": "https://iiif.archivelab.org/iiif/poems04hemagoog/manifest.json"
            },
            {
                "title": "Poems. Reprinted from the American octavo edition.",
                "url": "https://hdl.handle.net/2027/nyp.33433074905617",
                "date": "1827"
            },
            {
                "title": "Poems / by Mrs. Hemans.",
                "url": "https://hdl.handle.net/2027/hvd.hwkb5q",
                "date": "1827"
            },
            {
                "title": "Poems / by Mrs. Hemans.",
                "url": "https://hdl.handle.net/2027/hvd.hwkb69",
                "date": "1827"
            },
            {
                "title": "Poems / by Mrs. Hemans.",
                "url": "https://hdl.handle.net/2027/hvd.hwkb5j",
                "date": "1827"
            },
            {
                "title": "Poems / by Mrs. Hemans.",
                "url": "https://hdl.handle.net/2027/hvd.32044014402804",
                "date": "1827"
            },
            {
                "title": "Poems ... Reprinted from the American octavo edition.",
                "url": "https://hdl.handle.net/2027/hvd.hn6p36",
                "date": "1827"
            },
            {
                "title": "Poems ... Reprinted from the American octavo edition.",
                "url": "https://hdl.handle.net/2027/hvd.hn6p39",
                "date": "1827"
            },
            {
                "title": "The forest sanctuary : and other poems.",
                "url": "https://hdl.handle.net/2027/pst.000006234171",
                "date": "1827"
            },
            {
                "title": "Poems / by Mrs. Hemans.",
                "url": "https://hdl.handle.net/2027/hvd.hwkb54",
                "date": "1827"
            },
            {
                "title": "Poems / by Mrs. Hemans.",
                "url": "https://hdl.handle.net/2027/hvd.32044014402713",
                "date": "1827"
            },
            {
                "title": "Poems / by Mrs. Felicia Hemans.",
                "url": "https://hdl.handle.net/2027/hvd.hn6jzs",
                "date": "1827"
            },
            {
                "title": "Poems / by Mrs. Felicia Hemans.",
                "url": "https://hdl.handle.net/2027/hvd.hws4fr",
                "date": "1827"
            },
            {
                "title": "Records of woman : with other poems",
                "url": "https://archive.org/details/recordsofwomanwi00hemarich",
                "date": "1828",
                "iiif": "https://iiif.archivelab.org/iiif/recordsofwomanwi00hemarich/manifest.json"
            },
            {
                "title": "Records of woman: with other poems. By Felicia Hemans ...",
                "url": "https://hdl.handle.net/2027/nyp.33433074907183",
                "date": "1828"
            },
            {
                "title": "Poems : a new edition / by Mrs. Felicia Hemans.",
                "url": "https://hdl.handle.net/2027/hvd.32044090336983",
                "date": "1828"
            },
            {
                "title": "The poetical work of Mrs. Felicia Hemans.",
                "url": "https://hdl.handle.net/2027/hvd.hn6ki9",
                "date": "1828"
            },
            {
                "title": "Poems : a new edition / by Mrs. Felicia Hemans.",
                "url": "https://hdl.handle.net/2027/hvd.32044086789005",
                "date": "1828"
            },
            {
                "title": "The poetical work of Mrs. Felicia Hemans.",
                "url": "https://hdl.handle.net/2027/hvd.hn6kis",
                "date": "1828"
            },
            {
                "title": "The forest sanctuary; and other poems.",
                "url": "http://purl.ox.ac.uk/uuid/072a2f85d0314419955594b112303675",
                "date": "1829"
            },
            {
                "title": "Songs of the affections with other poems",
                "url": "https://archive.org/details/songsofaffection00hemarich",
                "date": "1830",
                "iiif": "https://iiif.archivelab.org/iiif/songsofaffection00hemarich/manifest.json"
            },
            {
                "title": "A discourse delivered at Dorchester on 17 June 1830 to commemorate the completion of the second century from its settlement by our Pilgrim fathers. ..",
                "url": "https://archive.org/details/discoursedeliver1830pier",
                "date": "1830",
                "iiif": "https://iiif.archivelab.org/iiif/discoursedeliver1830pier/manifest.json"
            },
            {
                "title": "The poetical works of Hemans, Heber and Pollok. Complete in one volume. Stereotyped by J. Crissy and G. Goodman.",
                "url": "https://hdl.handle.net/2027/nyp.33433074906417",
                "date": "1831"
            },
            {
                "title": "The poetical works of Hemans, Heber and Pollok.",
                "url": "https://hdl.handle.net/2027/uva.x030804449",
                "date": "1831"
            },
            {
                "title": "The poetical works of Hemans, Heber and Pollok. Complete in one volume. Stereotyped by J. Crissy and G. Goodman.",
                "url": "https://hdl.handle.net/2027/umn.319510020883736",
                "date": "1831"
            },
            {
                "title": "The poetical works of Mrs. Hemans.",
                "url": "https://hdl.handle.net/2027/uiug.30112054269912",
                "date": "1832"
            },
            {
                "title": "Poems / by Mrs. Felicia Hemans ; with a preface by the American editor.",
                "url": "https://hdl.handle.net/2027/hvd.hwkb91",
                "date": "1833"
            },
            {
                "title": "Poems / by Mrs. Felicia Hemans ; with a preface by the American editor.",
                "url": "https://hdl.handle.net/2027/hvd.hwkb9p",
                "date": "1833"
            },
            {
                "title": "The poetical works of Hemans, Heber, and Pollok.",
                "url": "https://hdl.handle.net/2027/hvd.32044086789013",
                "date": "1833"
            },
            {
                "title": "The poetical works of Hemaine, Heber and Pollok.",
                "url": "https://hdl.handle.net/2027/loc.ark:/13960/t3mw35x5w",
                "date": "1834"
            },
            {
                "title": "National lyrics : and songs for music",
                "url": "https://archive.org/details/nationallyricsso00hemarich",
                "date": "1834",
                "iiif": "https://iiif.archivelab.org/iiif/nationallyricsso00hemarich/manifest.json"
            },
            {
                "title": "The poetical works of Hemaine Heber and Pollok",
                "url": "https://archive.org/details/poeticalworksofh00hema",
                "date": "1834",
                "iiif": "https://iiif.archivelab.org/iiif/poeticalworksofh00hema/manifest.json"
            },
            {
                "title": "Poems",
                "url": "https://archive.org/details/poemsfel00hemaiala",
                "date": "1835",
                "iiif": "https://iiif.archivelab.org/iiif/poemsfel00hemaiala/manifest.json"
            },
            {
                "title": "Poems, by Mrs. Hemans.",
                "url": "https://hdl.handle.net/2027/uc2.ark:/13960/t6833r37x",
                "date": "1835"
            },
            {
                "title": "The forest sanctuary: with other poems. By Felicia Hemans.",
                "url": "https://hdl.handle.net/2027/nyp.33433074905377",
                "date": "1835"
            },
            {
                "title": "Songs of the affections, with other poems / by Felicia Hemans.",
                "url": "https://hdl.handle.net/2027/njp.32101017167048",
                "date": "1835"
            }
        ],
        "viaf": "https://viaf.org/viaf/17397168/",
        "wd": "https://www.wikidata.org/wiki/Q272537",
        "desc": "English poet (1793-1835)",
        "enwiki": "https://en.wikipedia.org/wiki/Felicia_Hemans",
        "enwikisource": "https://en.wikisource.org/wiki/Author:Felicia_Dorothea_Hemans"
    }
}