{
    "pers00472": {
        "id": "pers00472",
        "occ": [
            "poet",
            "writer"
        ],
        "cerl": "https://data.cerl.org/thesaurus/cnp01430871",
        "pseud": [
            "Janko Maginhradsk\u00fd"
        ],
        "wcat": "https://www.worldcat.org/identities/lccn-n82097614/",
        "viaf": "https://viaf.org/viaf/51702951/",
        "wd": "https://www.wikidata.org/wiki/Q974206",
        "desc": "Slovak poet and writer",
        "enwiki": "https://en.wikipedia.org/wiki/J%C3%A1n_Botto",
        "skwiki": "https://sk.wikipedia.org/wiki/J%C3%A1n_Botto",
        "otw": [
            {
                "title": "Spevy.",
                "url": "https://hdl.handle.net/2027/hvd.hwxt15",
                "date": "1880"
            }
        ],
        "ernie": "https://ernie.uva.nl/viewer.p/21/56/object/131-250673"
    }
}