{
    "pers00562": {
        "id": "pers00562",
        "occ": [
            "writer",
            "poet",
            "literary critic",
            "poet lawyer"
        ],
        "cerl": "https://data.cerl.org/thesaurus/cnp02127217",
        "wcat": "https://www.worldcat.org/identities/lccn-n96028249/",
        "viaf": "https://viaf.org/viaf/807363/",
        "wd": "https://www.wikidata.org/wiki/Q105016",
        "desc": "German writer",
        "enwiki": "https://en.wikipedia.org/wiki/Otto_Heinrich_von_Loeben",
        "dewiki": "https://de.wikipedia.org/wiki/Otto_von_Loeben",
        "dewikisource": "https://de.wikisource.org/wiki/Otto_von_Loeben"
    }
}
