{
    "pers00305": {
        "id": "pers00305",
        "occ": [
            "literary critic",
            "writer",
            "translator"
        ],
        "cerl": "https://data.cerl.org/thesaurus/cnp00911355",
        "wcat": "https://www.worldcat.org/identities/lccn-n86055038/",
        "viaf": "https://viaf.org/viaf/95307649/",
        "wd": "https://www.wikidata.org/wiki/Q77271",
        "desc": "German literary critic and writer",
        "enwiki": "https://en.wikipedia.org/wiki/Dorothea_von_Schlegel",
        "dewiki": "https://de.wikipedia.org/wiki/Dorothea_Schlegel",
        "dewikisource": "https://de.wikisource.org/wiki/Dorothea_Schlegel",
        "otw": [
            {
                "title": "Sammlung romantischer Dichtungen des Mitelalters :",
                "url": "https://archive.org/details/sammlungromantis11schl",
                "date": "1804",
                "iiif": "https://iiif.archivelab.org/iiif/sammlungromantis11schl/manifest.json"
            }
        ],
        "ernie": "https://ernie.uva.nl/viewer.p/21/56/object/131-278518"
    }
}